huilinnext/__init__.py
huilinnext/printsecond.py
forhuilin-1.0.0.dist-info/METADATA
forhuilin-1.0.0.dist-info/WHEEL
forhuilin-1.0.0.dist-info/top_level.txt
forhuilin-1.0.0.dist-info/RECORD
