Metadata-Version: 2.1
Name: forhuilin
Version: 1.0.0
Summary: A print test for PyPI
Home-page: https://www.python.org/
Author: winycg
Author-email: UNKNOWN
License: UNKNOWN
Platform: UNKNOWN
